{"season": 2018, "seasonType": "REG", "week": 7, "filter": "ALL", "threshold": 10, "stats": [{"avgTimeToLos": 2.651777777777778, "expectedRushYards": 41.5647753139737, "rushAttempts": 10, "rushPctOverExpected": 0.4, "rushTouchdowns": 0, "rushYards": 36, "rushYardsOverExpected": -5.564775313973698, "rushYardsOverExpectedPerAtt": -0.5564775313973698, "player": {"season": 2018, "seasonType": "REG", "week": 7, "currentTeamId": "3200", "displayName": "Kenjon Barner", "esbId": "BAR236353", "firstName": "Kenjon", "footballName": "Kenjon", "gsisId": "00-0030465", "gsisItId": 40130, "jerseyNumber": 38, "lastName": "Barner", "position": "RB", "positionGroup": "RB", "shortName": "K.Barner", "status": "ACT", "ngsPosition": "RB", "ngsPositionGroup": "RB", "smartId": "32004241-5223-6353-7eec-f76b08d3f9a0", "headshot": "https://static.www.nfl.com/image/private/{formatInstructions}/league/o5u78mg6kkt7zalhcbwj"}, "teamId": "3200", "efficiency": 4.683055555555556, "percentAttemptsGteEightDefenders": 30, "avgRushYards": 3.6}, {"avgTimeToLos": 2.495, "expectedRushYards": 75.47413308162754, "rushAttempts": 13, "rushPctOverExpected": 0.46153846153846156, "rushTouchdowns": 0, "rushYards": 65, "rushYardsOverExpected": -10.474133081627542, "rushYardsOverExpectedPerAtt": -0.8057025447405801, "player": {"season": 2018, "seasonType": "REG", "week": 7, "currentTeamId": "2510", "displayName": "Malcolm Brown", "esbId": "BRO550137", "firstName": "Malcolm", "footballName": "Malcolm", "gsisId": "00-0031806", "gsisItId": 42837, "jerseyNumber": 34, "lastName": "Brown", "position": "RB", "positionGroup": "RB", "shortName": "M.Brown", "status": "ACT", "ngsPosition": "RB", "ngsPositionGroup": "RB", "smartId": "32004252-4f55-0137-a08a-164e95f5f50c", "headshot": "https://static.www.nfl.com/image/private/{formatInstructions}/league/saroibi2giakpauwanjg"}, "teamId": "2510", "efficiency": 3.308769230769231, "percentAttemptsGteEightDefenders": 30.76923076923077, "avgRushYards": 5}, {"avgTimeToLos": 2.4829999999999997, "expectedRushYards": 45.35896283673041, "rushAttempts": 14, "rushPctOverExpected": 0.38461538461538464, "rushTouchdowns": 0, "rushYards": 39, "rushYardsOverExpected": -7.358962836730413, "rushYardsOverExpectedPerAtt": -0.566074064363878, "player": {"season": 2018, "seasonType": "REG", "week": 7, "currentTeamId": "3800", "displayName": "David Johnson", "esbId": "JOH174477", "firstName": "David", "footballName": "David", "gsisId": "00-0032187", "gsisItId": 42429, "jerseyNumber": 31, "lastName": "Johnson", "position": "RB", "positionGroup": "RB", "shortName": "D.Johnson", "status": "ACT", "ngsPosition": "RB", "ngsPositionGroup": "RB", "smartId": "32004a4f-4817-4477-4e5f-db6fb5a95abe", "headshot": "https://static.www.nfl.com/image/private/{formatInstructions}/league/ekmnsysofzigrqtetwmx"}, "teamId": "3800", "efficiency": 4.113846153846154, "percentAttemptsGteEightDefenders": 42.857142857142854, "avgRushYards": 2.7857142857142856}, {"avgTimeToLos": 2.5769, "expectedRushYards": 49.075139597845144, "rushAttempts": 10, "rushPctOverExpected": 0.4, "rushTouchdowns": 1, "rushYards": 50, "rushYardsOverExpected": 0.9248604021548559, "rushYardsOverExpectedPerAtt": 0.0924860402154856, "player": {"season": 2018, "seasonType": "REG", "week": 7, "currentTeamId": "1540", "displayName": "LeGarrette Blount", "esbId": "BLO626278", "firstName": "LeGarrette", "footballName": "LeGarrette", "gsisId": "00-0027325", "gsisItId": 35838, "jerseyNumber": 29, "lastName": "Blount", "position": "RB", "positionGroup": "RB", "shortName": "L.Blount", "status": "ACT", "ngsPosition": "RB", "ngsPositionGroup": "RB", "smartId": "3200424c-4f62-6278-90e7-1045a3f929f4", "headshot": "https://static.www.nfl.com/image/private/{formatInstructions}/league/s3eilto1yi0yhoamvvo3"}, "teamId": "1540", "efficiency": 3.2533999999999996, "percentAttemptsGteEightDefenders": 30, "avgRushYards": 5}, {"avgTimeToLos": 2.8892500000000005, "expectedRushYards": 49.493697924998074, "rushAttempts": 11, "rushPctOverExpected": 0.18181818181818182, "rushTouchdowns": 1, "rushYards": 50, "rushYardsOverExpected": 0.5063020750019263, "rushYardsOverExpectedPerAtt": 0.04602746136381148, "player": {"season": 2018, "seasonType": "REG", "week": 7, "currentTeamId": "0200", "displayName": "Tevin Coleman", "esbId": "COL359050", "firstName": "Tevin", "footballName": "Tevin", "gsisId": "00-0032058", "gsisItId": 42416, "jerseyNumber": 26, "lastName": "Coleman", "position": "RB", "positionGroup": "RB", "shortName": "T.Coleman", "status": "ACT", "ngsPosition": "RB", "ngsPositionGroup": "RB", "smartId": "3200434f-4c35-9050-eb7e-20c726e53f5b", "headshot": "https://static.www.nfl.com/image/private/{formatInstructions}/league/nabesbpd8nocsy6aplmj"}, "teamId": "0200", "efficiency": 4.6696, "percentAttemptsGteEightDefenders": 36.36363636363637, "avgRushYards": 4.545454545454546}, {"avgTimeToLos": 2.9815, "expectedRushYards": 45.38318988840424, "rushAttempts": 12, "rushPctOverExpected": 0.25, "rushTouchdowns": 0, "rushYards": 28, "rushYardsOverExpected": -17.38318988840424, "rushYardsOverExpectedPerAtt": -1.4485991573670198, "player": {"season": 2018, "seasonType": "REG", "week": 7, "currentTeamId": "2250", "displayName": "T.J. Yeldon", "esbId": "YEL060186", "firstName": "Timothy", "footballName": "T.J.", "gsisId": "00-0032209", "gsisItId": 42379, "jerseyNumber": 24, "lastName": "Yeldon", "position": "RB", "positionGroup": "RB", "shortName": "T.Yeldon", "status": "ACT", "suffix": "Jr.", "ngsPosition": "RB", "ngsPositionGroup": "RB", "smartId": "32005945-4c06-0186-cd0f-a93c74a0d6a6", "headshot": "https://static.www.nfl.com/image/private/{formatInstructions}/league/upd4s91rxtbdylyydqxq"}, "teamId": "2250", "efficiency": 5.365357142857143, "percentAttemptsGteEightDefenders": 8.333333333333332, "avgRushYards": 2.3333333333333335}, {"avgTimeToLos": 2.930272727272728, "expectedRushYards": 30.93379566748111, "rushAttempts": 11, "rushPctOverExpected": 0.6363636363636364, "rushTouchdowns": 0, "rushYards": 40, "rushYardsOverExpected": 9.06620433251889, "rushYardsOverExpectedPerAtt": 0.8242003938653536, "player": {"season": 2018, "seasonType": "REG", "week": 7, "currentTeamId": "3200", "displayName": "James White", "esbId": "WHI242257", "firstName": "James", "footballName": "James", "gsisId": "00-0031062", "gsisItId": 41359, "jerseyNumber": 28, "lastName": "White", "position": "RB", "positionGroup": "RB", "shortName": "J.White", "status": "ACT", "ngsPosition": "RB", "ngsPositionGroup": "RB", "smartId": "32005748-4924-2257-cf66-816145cac5b1", "headshot": "https://static.www.nfl.com/image/private/{formatInstructions}/league/l1ygfmpyz5hbbzrhyjug"}, "teamId": "3200", "efficiency": 5.05175, "percentAttemptsGteEightDefenders": 27.27272727272727, "avgRushYards": 3.6363636363636362}, {"avgTimeToLos": 2.262181818181818, "expectedRushYards": 47.36185132154974, "rushAttempts": 12, "rushPctOverExpected": 0.3333333333333333, "rushTouchdowns": 1, "rushYards": 33, "rushYardsOverExpected": -14.361851321549743, "rushYardsOverExpectedPerAtt": -1.1968209434624786, "player": {"season": 2018, "seasonType": "REG", "week": 7, "currentTeamId": "2100", "displayName": "Derrick Henry", "esbId": "HEN602843", "firstName": "Derrick", "footballName": "Derrick", "gsisId": "00-0032764", "gsisItId": 43334, "jerseyNumber": 22, "lastName": "Henry", "position": "RB", "positionGroup": "RB", "shortName": "D.Henry", "status": "ACT", "suffix": "Jr.", "ngsPosition": "RB", "ngsPositionGroup": "RB", "smartId": "32004845-4e60-2843-9b64-3cd8fac319c3", "headshot": "https://static.www.nfl.com/image/private/{formatInstructions}/league/vygpdc31jwc0zrusaeg5"}, "teamId": "2100", "efficiency": 4.535757575757576, "percentAttemptsGteEightDefenders": 25, "avgRushYards": 2.75}, {"avgTimeToLos": 2.742666666666667, "expectedRushYards": 89.28540444921671, "rushAttempts": 22, "rushPctOverExpected": 0.5, "rushTouchdowns": 1, "rushYards": 100, "rushYardsOverExpected": 10.714595550783287, "rushYardsOverExpectedPerAtt": 0.48702707049014937, "player": {"season": 2018, "seasonType": "REG", "week": 7, "currentTeamId": "2120", "displayName": "Lamar Miller", "esbId": "MIL373118", "firstName": "Lamar", "footballName": "Lamar", "gsisId": "00-0029615", "gsisItId": 38627, "jerseyNumber": 26, "lastName": "Miller", "position": "RB", "positionGroup": "RB", "shortName": "L.Miller", "status": "ACT", "ngsPosition": "RB", "ngsPositionGroup": "RB", "smartId": "32004d49-4c37-3118-7861-c1aecae47732", "headshot": "https://static.www.nfl.com/image/private/{formatInstructions}/league/b0ggwcqngfyq7ccyksgv"}, "teamId": "2120", "efficiency": 3.3477000000000006, "percentAttemptsGteEightDefenders": 22.727272727272727, "avgRushYards": 4.545454545454546}, {"avgTimeToLos": 2.365, "expectedRushYards": 34.070773741485255, "rushAttempts": 10, "rushPctOverExpected": 0.3, "rushTouchdowns": 0, "rushYards": 29, "rushYardsOverExpected": -5.0707737414852545, "rushYardsOverExpectedPerAtt": -0.5070773741485255, "player": {"season": 2018, "seasonType": "REG", "week": 7, "currentTeamId": "2700", "displayName": "Frank Gore", "esbId": "GOR411171", "firstName": "Frank", "footballName": "Frank", "gsisId": "00-0023500", "gsisItId": 29892, "jerseyNumber": 21, "lastName": "Gore", "position": "RB", "positionGroup": "RB", "shortName": "F.Gore", "status": "ACT", "ngsPosition": "RB", "ngsPositionGroup": "RB", "smartId": "3200474f-5241-1171-e932-18530d86ff0c", "headshot": "https://static.www.nfl.com/image/private/{formatInstructions}/league/lxxkhd2suyalrbruzut7"}, "teamId": "2700", "efficiency": 4.126206896551723, "percentAttemptsGteEightDefenders": 0, "avgRushYards": 2.9}, {"avgTimeToLos": 2.433923076923077, "expectedRushYards": 95.81175414465731, "rushAttempts": 15, "rushPctOverExpected": 0.06666666666666667, "rushTouchdowns": 2, "rushYards": 63, "rushYardsOverExpected": -32.811754144657314, "rushYardsOverExpectedPerAtt": -2.1874502763104875, "player": {"season": 2018, "seasonType": "REG", "week": 7, "currentTeamId": "2510", "displayName": "Todd Gurley", "esbId": "GUR000000", "firstName": "Todd", "footballName": "Todd", "gsisId": "00-0032241", "gsisItId": 42353, "jerseyNumber": 30, "lastName": "Gurley", "position": "RB", "positionGroup": "RB", "shortName": "T.Gurley", "status": "ACT", "suffix": "II", "ngsPosition": "RB", "ngsPositionGroup": "RB", "smartId": "32004755-5200-0000-f496-e727c8f2225d", "headshot": "https://static.www.nfl.com/image/private/{formatInstructions}/league/cowureyhghi80oxpmvjq"}, "teamId": "2510", "efficiency": 3.8538095238095242, "percentAttemptsGteEightDefenders": 0, "avgRushYards": 4.2}, {"avgTimeToLos": 2.5619, "expectedRushYards": 47.55350878550527, "rushAttempts": 11, "rushPctOverExpected": 0.18181818181818182, "rushTouchdowns": 0, "rushYards": 29, "rushYardsOverExpected": -18.553508785505272, "rushYardsOverExpectedPerAtt": -1.6866826168641156, "player": {"season": 2018, "seasonType": "REG", "week": 7, "currentTeamId": "3430", "displayName": "Isaiah Crowell", "esbId": "CRO734794", "firstName": "Isaiah", "footballName": "Isaiah", "gsisId": "00-0030656", "gsisItId": 41493, "jerseyNumber": 20, "lastName": "Crowell", "position": "RB", "positionGroup": "RB", "shortName": "I.Crowell", "status": "ACT", "ngsPosition": "RB", "ngsPositionGroup": "RB", "smartId": "32004352-4f73-4794-4e0a-a192aa40d05c", "headshot": "https://static.www.nfl.com/image/private/{formatInstructions}/league/oruiw5myfimtssv6j2ar"}, "teamId": "3430", "efficiency": 5.198620689655173, "percentAttemptsGteEightDefenders": 36.36363636363637, "avgRushYards": 2.6363636363636362}, {"avgTimeToLos": 3.233461538461538, "expectedRushYards": 36.96381303086326, "rushAttempts": 14, "rushPctOverExpected": 0.42857142857142855, "rushTouchdowns": 1, "rushYards": 43, "rushYardsOverExpected": 6.036186969136743, "rushYardsOverExpectedPerAtt": 0.4311562120811959, "player": {"season": 2018, "seasonType": "REG", "week": 7, "currentTeamId": "3410", "displayName": "Saquon Barkley", "esbId": "BAR192674", "firstName": "Saquon", "footballName": "Saquon", "gsisId": "00-0034844", "gsisItId": 46208, "jerseyNumber": 26, "lastName": "Barkley", "position": "RB", "positionGroup": "RB", "shortName": "S.Barkley", "status": "ACT", "ngsPosition": "RB", "ngsPositionGroup": "RB", "smartId": "32004241-5219-2674-af43-1519254e563d", "headshot": "https://static.www.nfl.com/image/private/{formatInstructions}/league/yimxr0tykw7u3aogj60u"}, "teamId": "3410", "efficiency": 5.8427906976744195, "percentAttemptsGteEightDefenders": 28.57142857142857, "avgRushYards": 3.0714285714285716}, {"avgTimeToLos": 3.152277777777777, "expectedRushYards": 105.43653624450144, "rushAttempts": 24, "rushPctOverExpected": 0.16666666666666666, "rushTouchdowns": 0, "rushYards": 99, "rushYardsOverExpected": -6.43653624450144, "rushYardsOverExpectedPerAtt": -0.26818901018756, "player": {"season": 2018, "seasonType": "REG", "week": 7, "currentTeamId": "5110", "displayName": "Adrian Peterson", "esbId": "PET260705", "firstName": "Adrian", "footballName": "Adrian", "gsisId": "00-0025394", "gsisItId": 32200, "jerseyNumber": 26, "lastName": "Peterson", "position": "RB", "positionGroup": "RB", "shortName": "A.Peterson", "status": "ACT", "ngsPosition": "RB", "ngsPositionGroup": "RB", "smartId": "32005045-5426-0705-afaf-b095105b31fb", "headshot": "https://static.www.nfl.com/image/private/{formatInstructions}/league/lfgv8vf2abbvuoaibr8r"}, "teamId": "5110", "efficiency": 4.687070707070707, "percentAttemptsGteEightDefenders": 29.166666666666668, "avgRushYards": 4.125}, {"avgTimeToLos": 3.0114615384615386, "expectedRushYards": 53.85194152107514, "rushAttempts": 16, "rushPctOverExpected": 0.4375, "rushTouchdowns": 0, "rushYards": 81, "rushYardsOverExpected": 27.14805847892486, "rushYardsOverExpectedPerAtt": 1.6967536549328037, "player": {"season": 2018, "seasonType": "REG", "week": 7, "currentTeamId": "0610", "displayName": "Chris Ivory", "esbId": "IVO253611", "firstName": "Christopher", "footballName": "Chris", "gsisId": "00-0027531", "gsisItId": 36052, "jerseyNumber": 33, "lastName": "Ivory", "position": "RB", "positionGroup": "RB", "shortName": "C.Ivory", "status": "ACT", "ngsPosition": "RB", "ngsPositionGroup": "RB", "smartId": "32004956-4f25-3611-afa1-32a4ef3b7338", "headshot": "https://static.www.nfl.com/image/private/{formatInstructions}/league/wuhrkffigvt55hcqd4yw"}, "teamId": "0610", "efficiency": 3.151234567901234, "percentAttemptsGteEightDefenders": 0, "avgRushYards": 5.0625}, {"avgTimeToLos": 2.586090909090909, "expectedRushYards": 46.01613831629728, "rushAttempts": 12, "rushPctOverExpected": 0.18181818181818182, "rushTouchdowns": 0, "rushYards": 32, "rushYardsOverExpected": -16.01613831629728, "rushYardsOverExpectedPerAtt": -1.4560125742088437, "player": {"season": 2018, "seasonType": "REG", "week": 7, "currentTeamId": "3300", "displayName": "Mark Ingram", "esbId": "ING656964", "firstName": "Mark", "footballName": "Mark", "gsisId": "00-0027966", "gsisItId": 37101, "jerseyNumber": 22, "lastName": "Ingram", "position": "RB", "positionGroup": "RB", "shortName": "M.Ingram", "status": "ACT", "suffix": "Jr.", "ngsPosition": "RB", "ngsPositionGroup": "RB", "smartId": "3200494e-4765-6964-19af-4fbe814368d2", "headshot": "https://static.www.nfl.com/image/private/{formatInstructions}/league/ky9yy9cme3vh3y58rj9w"}, "teamId": "3300", "efficiency": 4.5603125, "percentAttemptsGteEightDefenders": 33.33333333333333, "avgRushYards": 2.6666666666666665}, {"avgTimeToLos": 2.462583333333334, "expectedRushYards": 51.32284469242334, "rushAttempts": 12, "rushPctOverExpected": 0.16666666666666666, "rushTouchdowns": 1, "rushYards": 39, "rushYardsOverExpected": -12.322844692423338, "rushYardsOverExpectedPerAtt": -1.0269037243686114, "player": {"season": 2018, "seasonType": "REG", "week": 7, "currentTeamId": "0810", "displayName": "Jordan Howard", "esbId": "HOW239418", "firstName": "Jordan", "footballName": "Jordan", "gsisId": "00-0032780", "gsisItId": 43439, "jerseyNumber": 24, "lastName": "Howard", "position": "RB", "positionGroup": "RB", "shortName": "J.Howard", "status": "ACT", "ngsPosition": "RB", "ngsPositionGroup": "RB", "smartId": "3200484f-5723-9418-9826-088b7176f34d", "headshot": "https://static.www.nfl.com/image/private/{formatInstructions}/league/zgrflibbgonhzudexdlr"}, "teamId": "0810", "efficiency": 3.7738461538461547, "percentAttemptsGteEightDefenders": 33.33333333333333, "avgRushYards": 3.25}, {"avgTimeToLos": 3.1336923076923076, "expectedRushYards": 61.88787352737806, "rushAttempts": 13, "rushPctOverExpected": 0.25, "rushTouchdowns": 0, "rushYards": 50, "rushYardsOverExpected": -14.887873527378062, "rushYardsOverExpectedPerAtt": -1.240656127281505, "player": {"season": 2018, "seasonType": "REG", "week": 7, "currentTeamId": "0920", "displayName": "Joe Mixon", "esbId": "MIX564388", "firstName": "Joe", "footballName": "Joe", "gsisId": "00-0033897", "gsisItId": 44860, "jerseyNumber": 28, "lastName": "Mixon", "position": "HB", "positionGroup": "RB", "shortName": "J.Mixon", "status": "ACT", "ngsPosition": "RB", "ngsPositionGroup": "RB", "smartId": "32004d49-5856-4388-c611-05b6fcff1d1d", "headshot": "https://static.www.nfl.com/image/private/{formatInstructions}/league/pkzlqusxfp1pioew4pb3"}, "teamId": "0920", "efficiency": 4.210000000000001, "percentAttemptsGteEightDefenders": 0, "avgRushYards": 3.8461538461538463}, {"avgTimeToLos": 2.6464166666666666, "expectedRushYards": 48.042600802735485, "rushAttempts": 15, "rushPctOverExpected": 0.42857142857142855, "rushTouchdowns": 2, "rushYards": 69, "rushYardsOverExpected": 13.957399197264515, "rushYardsOverExpectedPerAtt": 0.996957085518894, "player": {"season": 2018, "seasonType": "REG", "week": 7, "currentTeamId": "3000", "displayName": "Latavius Murray", "esbId": "MUR671046", "firstName": "Latavius", "footballName": "Latavius", "gsisId": "00-0030513", "gsisItId": 40129, "jerseyNumber": 25, "lastName": "Murray", "position": "RB", "positionGroup": "RB", "shortName": "L.Murray", "status": "ACT", "ngsPosition": "RB", "ngsPositionGroup": "RB", "smartId": "32004d55-5267-1046-5487-d03e83f25c8b", "headshot": "https://static.www.nfl.com/image/private/{formatInstructions}/league/xoc3ipmwmfx9x7chlreq"}, "teamId": "3000", "efficiency": 3.273333333333333, "percentAttemptsGteEightDefenders": 20, "avgRushYards": 4.6}, {"avgTimeToLos": 3.185277777777778, "expectedRushYards": 78.36602634941883, "rushAttempts": 19, "rushPctOverExpected": 0.5263157894736842, "rushTouchdowns": 0, "rushYards": 158, "rushYardsOverExpected": 79.63397365058117, "rushYardsOverExpectedPerAtt": 4.191261771083219, "player": {"season": 2018, "seasonType": "REG", "week": 7, "currentTeamId": "1540", "displayName": "Kerryon Johnson", "esbId": "JOH399188", "firstName": "Kerryon", "footballName": "Kerryon", "gsisId": "00-0034349", "gsisItId": 46112, "jerseyNumber": 33, "lastName": "Johnson", "position": "RB", "positionGroup": "RB", "shortName": "K.Johnson", "status": "ACT", "ngsPosition": "RB", "ngsPositionGroup": "RB", "smartId": "32004a4f-4839-9188-cb7b-f29b5ea64839", "headshot": "https://static.www.nfl.com/image/private/{formatInstructions}/league/vgfy6zk6f4f8kwslxrje"}, "teamId": "1540", "efficiency": 2.5493037974683546, "percentAttemptsGteEightDefenders": 26.31578947368421, "avgRushYards": 8.31578947368421}, {"avgTimeToLos": 3.2706153846153847, "expectedRushYards": 36.148256092884765, "rushAttempts": 13, "rushPctOverExpected": 0.6153846153846154, "rushTouchdowns": 1, "rushYards": 37, "rushYardsOverExpected": 0.8517439071152353, "rushYardsOverExpectedPerAtt": 0.06551876208578733, "player": {"season": 2018, "seasonType": "REG", "week": 7, "currentTeamId": "1400", "displayName": "Royce Freeman", "esbId": "FRE376456", "firstName": "Royce", "footballName": "Royce", "gsisId": "00-0034838", "gsisItId": 46140, "jerseyNumber": 28, "lastName": "Freeman", "position": "RB", "positionGroup": "RB", "shortName": "R.Freeman", "status": "ACT", "suffix": "", "ngsPosition": "RB", "ngsPositionGroup": "RB", "smartId": "32004652-4537-6456-ac22-4a857061d9e4", "headshot": "https://static.www.nfl.com/image/private/{formatInstructions}/league/nra5de3elhezp77jqg5z"}, "teamId": "1400", "efficiency": 5.438648648648649, "percentAttemptsGteEightDefenders": 76.92307692307693, "avgRushYards": 2.8461538461538463}, {"avgTimeToLos": 3.0269, "expectedRushYards": 30.826891238816273, "rushAttempts": 11, "rushPctOverExpected": 0.45454545454545453, "rushTouchdowns": 0, "rushYards": 30, "rushYardsOverExpected": -0.8268912388162732, "rushYardsOverExpectedPerAtt": -0.07517193080147938, "player": {"season": 2018, "seasonType": "REG", "week": 7, "currentTeamId": "4900", "displayName": "Peyton Barber", "esbId": "BAR077733", "firstName": "Kenneth", "footballName": "Peyton", "gsisId": "00-0032741", "gsisItId": 43861, "jerseyNumber": 25, "lastName": "Barber", "position": "RB", "positionGroup": "RB", "shortName": "P.Barber", "status": "ACT", "ngsPosition": "RB", "ngsPositionGroup": "RB", "smartId": "32004241-5207-7733-5913-58201e96ca93", "headshot": "https://static.www.nfl.com/image/private/{formatInstructions}/league/srihb9x7yferacjmdhdt"}, "teamId": "4900", "efficiency": 5.060333333333333, "percentAttemptsGteEightDefenders": 36.36363636363637, "avgRushYards": 2.727272727272727}, {"avgTimeToLos": 2.817375, "expectedRushYards": 94.75772820802176, "rushAttempts": 19, "rushPctOverExpected": 0.47368421052631576, "rushTouchdowns": 1, "rushYards": 126, "rushYardsOverExpected": 31.24227179197824, "rushYardsOverExpectedPerAtt": 1.6443300943146442, "player": {"season": 2018, "seasonType": "REG", "week": 7, "currentTeamId": "2200", "displayName": "Marlon Mack", "esbId": "MAC338783", "firstName": "Marlon", "footballName": "Marlon", "gsisId": "00-0033951", "gsisItId": 44956, "jerseyNumber": 25, "lastName": "Mack", "position": "RB", "positionGroup": "RB", "shortName": "M.Mack", "status": "ACT", "ngsPosition": "RB", "ngsPositionGroup": "RB", "smartId": "32004d41-4333-8783-1057-4314041567c5", "headshot": "https://static.www.nfl.com/image/private/{formatInstructions}/league/unt9jomg4vkmatqez2f1"}, "teamId": "2200", "efficiency": 2.6013492063492065, "percentAttemptsGteEightDefenders": 42.10526315789473, "avgRushYards": 6.631578947368421}, {"avgTimeToLos": 2.7567500000000003, "expectedRushYards": 57.1449734712138, "rushAttempts": 18, "rushPctOverExpected": 0.5555555555555556, "rushTouchdowns": 1, "rushYards": 80, "rushYardsOverExpected": 22.855026528786198, "rushYardsOverExpectedPerAtt": 1.2697236960436777, "player": {"season": 2018, "seasonType": "REG", "week": 7, "currentTeamId": "1050", "displayName": "Nick Chubb", "esbId": "CHU033942", "firstName": "Nicholas", "footballName": "Nick", "gsisId": "00-0034791", "gsisItId": 46104, "jerseyNumber": 24, "lastName": "Chubb", "position": "RB", "positionGroup": "RB", "shortName": "N.Chubb", "status": "ACT", "ngsPosition": "RB", "ngsPositionGroup": "RB", "smartId": "32004348-5503-3942-d8b2-181bd658412e", "headshot": "https://static.www.nfl.com/image/private/{formatInstructions}/league/mp7o4isx8qzu4l1ju7ti"}, "teamId": "1050", "efficiency": 3.568875, "percentAttemptsGteEightDefenders": 11.11111111111111, "avgRushYards": 4.444444444444445}, {"avgTimeToLos": 2.6232727272727274, "expectedRushYards": 58.49855084470194, "rushAttempts": 14, "rushPctOverExpected": 0.42857142857142855, "rushTouchdowns": 1, "rushYards": 90, "rushYardsOverExpected": 31.50144915529806, "rushYardsOverExpectedPerAtt": 2.2501035110927186, "player": {"season": 2018, "seasonType": "REG", "week": 7, "currentTeamId": "1400", "displayName": "Phillip Lindsay", "esbId": "LIN303086", "firstName": "Phillip", "footballName": "Phillip", "gsisId": "00-0034109", "gsisItId": 46367, "jerseyNumber": 30, "lastName": "Lindsay", "position": "RB", "positionGroup": "RB", "shortName": "P.Lindsay", "status": "ACT", "ngsPosition": "RB", "ngsPositionGroup": "RB", "smartId": "32004c49-4e30-3086-a451-a8add609c5d0", "headshot": "https://static.www.nfl.com/image/private/{formatInstructions}/league/ulywgze6rhdk1kah9fyy"}, "teamId": "1400", "efficiency": 3.1787777777777775, "percentAttemptsGteEightDefenders": 14.285714285714285, "avgRushYards": 6.428571428571429}, {"avgTimeToLos": 2.6435999999999997, "expectedRushYards": 62.191735270757, "rushAttempts": 17, "rushPctOverExpected": 0.5294117647058824, "rushTouchdowns": 1, "rushYards": 64, "rushYardsOverExpected": 1.8082647292429996, "rushYardsOverExpectedPerAtt": 0.10636851348488233, "player": {"season": 2018, "seasonType": "REG", "week": 7, "currentTeamId": "3300", "displayName": "Alvin Kamara", "esbId": "KAM244058", "firstName": "Alvin", "footballName": "Alvin", "gsisId": "00-0033906", "gsisItId": 44879, "jerseyNumber": 41, "lastName": "Kamara", "position": "RB", "positionGroup": "RB", "shortName": "A.Kamara", "status": "ACT", "ngsPosition": "RB", "ngsPositionGroup": "RB", "smartId": "32004b41-4d24-4058-5a3b-01bd39e6a25d", "headshot": "https://static.www.nfl.com/image/private/{formatInstructions}/league/xs7zkncnl9261b101wo9"}, "teamId": "3300", "efficiency": 4.251875, "percentAttemptsGteEightDefenders": 5.88235294117647, "avgRushYards": 3.764705882352941}, {"avgTimeToLos": 2.7505, "expectedRushYards": 54.183239717708624, "rushAttempts": 15, "rushPctOverExpected": 0.3333333333333333, "rushTouchdowns": 0, "rushYards": 33, "rushYardsOverExpected": -21.183239717708624, "rushYardsOverExpectedPerAtt": -1.412215981180575, "player": {"season": 2018, "seasonType": "REG", "week": 7, "currentTeamId": "1200", "displayName": "Ezekiel Elliott", "esbId": "ELL289284", "firstName": "Ezekiel", "footballName": "Ezekiel", "gsisId": "00-0033045", "gsisItId": 43293, "jerseyNumber": 21, "lastName": "Elliott", "position": "RB", "positionGroup": "RB", "shortName": "E.Elliott", "status": "ACT", "ngsPosition": "RB", "ngsPositionGroup": "RB", "smartId": "3200454c-4c28-9284-cdcc-74694c8d1749", "headshot": "https://static.www.nfl.com/image/private/{formatInstructions}/league/e2h7hohon748tyzzu3z5"}, "teamId": "1200", "efficiency": 7.2366666666666655, "percentAttemptsGteEightDefenders": 26.666666666666668, "avgRushYards": 2.2}, {"avgTimeToLos": 2.9667499999999998, "expectedRushYards": 38.719351863153435, "rushAttempts": 11, "rushPctOverExpected": 0.4, "rushTouchdowns": 0, "rushYards": 38, "rushYardsOverExpected": -4.719351863153435, "rushYardsOverExpectedPerAtt": -0.4719351863153435, "player": {"season": 2018, "seasonType": "REG", "week": 7, "currentTeamId": "0325", "displayName": "Alex Collins", "esbId": "COL479374", "firstName": "Alex", "footballName": "Alex", "gsisId": "00-0032426", "gsisItId": 43460, "jerseyNumber": 34, "lastName": "Collins", "position": "RB", "positionGroup": "RB", "shortName": "A.Collins", "status": "ACT", "ngsPosition": "RB", "ngsPositionGroup": "RB", "smartId": "3200434f-4c47-9374-2540-96fa3f4d7768", "headshot": "https://static.www.nfl.com/image/private/{formatInstructions}/league/wqtukgbvpamp4kbphyfz"}, "teamId": "0325", "efficiency": 4.778421052631579, "percentAttemptsGteEightDefenders": 18.181818181818183, "avgRushYards": 3.4545454545454546}, {"avgTimeToLos": 3.0936, "expectedRushYards": 52.53732206001591, "rushAttempts": 13, "rushPctOverExpected": 0.5384615384615384, "rushTouchdowns": 0, "rushYards": 91, "rushYardsOverExpected": 38.46267793998409, "rushYardsOverExpectedPerAtt": 2.95866753384493, "player": {"season": 2018, "seasonType": "REG", "week": 7, "currentTeamId": "2100", "displayName": "Dion Lewis", "esbId": "LEW218646", "firstName": "Dion", "footballName": "Dion", "gsisId": "00-0028087", "gsisItId": 37224, "jerseyNumber": 33, "lastName": "Lewis", "position": "RB", "positionGroup": "RB", "shortName": "D.Lewis", "status": "ACT", "ngsPosition": "RB", "ngsPositionGroup": "RB", "smartId": "32004c45-5721-8646-e7c5-72a7c65dcee8", "headshot": "https://static.www.nfl.com/image/private/{formatInstructions}/league/erzmtaaz3eimbg998hyq"}, "teamId": "2100", "efficiency": 3.109230769230769, "percentAttemptsGteEightDefenders": 15.384615384615385, "avgRushYards": 7}, {"avgTimeToLos": 3.0431999999999997, "expectedRushYards": 65.51416714013479, "rushAttempts": 15, "rushPctOverExpected": 0.5714285714285714, "rushTouchdowns": 1, "rushYards": 86, "rushYardsOverExpected": 17.485832859865212, "rushYardsOverExpectedPerAtt": 1.2489880614189437, "player": {"season": 2018, "seasonType": "REG", "week": 7, "currentTeamId": "2310", "displayName": "Kareem Hunt", "esbId": "HUN308934", "firstName": "Kareem", "footballName": "Kareem", "gsisId": "00-0033923", "gsisItId": 44898, "jerseyNumber": 27, "lastName": "Hunt", "position": "RB", "positionGroup": "RB", "shortName": "K.Hunt", "status": "ACT", "ngsPosition": "RB", "ngsPositionGroup": "RB", "smartId": "32004855-4e30-8934-bd0d-d8d3d09b6aac", "headshot": "https://static.www.nfl.com/image/private/{formatInstructions}/league/zv22qd2meecbnbpjwrhe"}, "teamId": "2310", "efficiency": 3.4061627906976746, "percentAttemptsGteEightDefenders": 6.666666666666667, "avgRushYards": 5.733333333333333}, {"avgTimeToLos": 3.005, "expectedRushYards": 67.82399647919014, "rushAttempts": 12, "rushPctOverExpected": 0.16666666666666666, "rushTouchdowns": 0, "rushYards": 42, "rushYardsOverExpected": -25.823996479190143, "rushYardsOverExpectedPerAtt": -2.1519997065991787, "player": {"season": 2018, "seasonType": "REG", "week": 7, "currentTeamId": "4400", "displayName": "Austin Ekeler", "esbId": "EKE189430", "firstName": "Austin", "footballName": "Austin", "gsisId": "00-0033699", "gsisItId": 45573, "jerseyNumber": 30, "lastName": "Ekeler", "position": "RB", "positionGroup": "RB", "shortName": "A.Ekeler", "status": "ACT", "ngsPosition": "RB", "ngsPositionGroup": "RB", "smartId": "3200454b-4518-9430-b8b6-2128b5b3e282", "headshot": "https://static.www.nfl.com/image/private/{formatInstructions}/league/kbo1ouatld3unac5ijrm"}, "teamId": "4400", "efficiency": 5.1745238095238095, "percentAttemptsGteEightDefenders": 25, "avgRushYards": 3.5}]}